__init__.py
Base/CustomExceptions.py
Base/EnforceTypes.py
Base/ModelBase.py
Base/RequestBase.py
Base/ResponseBase.py
Base/ValidParameters.py
Base/__init__.py
Models/__init__.py
Models/V1/Future.py
Models/V1/FutureOdds.py
Models/V1/Game.py
Models/V1/League.py
Models/V1/Market.py
Models/V1/Odds.py
Models/V1/PeriodScore.py
Models/V1/Score.py
Models/V1/__init__.py
Models/V2/Future.py
Models/V2/FutureOdds.py
Models/V2/Game.py
Models/V2/League.py
Models/V2/Market.py
Models/V2/Odds.py
Models/V2/PeriodScore.py
Models/V2/Score.py
Models/V2/__init__.py
OddsJamClient/OddsJamClient.py
OddsJamClient/__init__.py
OddsJamClient/V1/Requestor.py
OddsJamClient/V1/__init__.py
OddsJamClient/V2/Requestor.py
OddsJamClient/V2/__init__.py
Request/__init__.py
Request/V1/GetFutureOddsRequest.py
Request/V1/GetFuturesRequest.py
Request/V1/GetGamesRequest.py
Request/V1/GetLeaguesRequest.py
Request/V1/GetMarketsRequest.py
Request/V1/GetOddsRequest.py
Request/V1/GetScoresRequest.py
Request/V1/__init__.py
Request/V2/GetFutureOddsRequest.py
Request/V2/GetFuturesRequest.py
Request/V2/GetGamesRequest.py
Request/V2/GetLeaguesRequest.py
Request/V2/GetMarketsRequest.py
Request/V2/GetOddsRequest.py
Request/V2/GetScoresRequest.py
Request/V2/__init__.py
Response/__init__.py
Response/V1/GetFutureOddsResponse.py
Response/V1/GetFuturesResponse.py
Response/V1/GetGamesResponse.py
Response/V1/GetLeaguesResponse.py
Response/V1/GetMarketsResponse.py
Response/V1/GetOddsResponse.py
Response/V1/GetScoresResponse.py
Response/V1/__init__.py
Response/V2/GetFutureOddsResponse.py
Response/V2/GetFuturesResponse.py
Response/V2/GetGamesResponse.py
Response/V2/GetLeaguesResponse.py
Response/V2/GetMarketsResponse.py
Response/V2/GetOddsResponse.py
Response/V2/GetScoresResponse.py
Response/V2/__init__.py
oddsjam_api-0.2.9.dist-info/LICENSE
oddsjam_api-0.2.9.dist-info/METADATA
oddsjam_api-0.2.9.dist-info/WHEEL
oddsjam_api-0.2.9.dist-info/top_level.txt
oddsjam_api-0.2.9.dist-info/RECORD
