Metadata-Version: 2.1
Name: oddsjam-api
Version: 0.2.9
Summary: A lightweight OddsJam API wrapper
Author-email: Rohan Challa <rchalla769@gmail.com>, Brandon Cooper <cooper.brandon@outlook.com>
Project-URL: Homepage, https://github.com/oddsjam/api-python
Project-URL: Bug Tracker, https://github.com/oddsjam/api-python/issues
Classifier: Programming Language :: Python :: 3
Classifier: License :: OSI Approved :: MIT License
Classifier: Operating System :: OS Independent
Requires-Python: >=3.7
License-File: LICENSE
